LICENSE
README.md
docs/Makefile
docs/make.bat
docs/source/acknowledgments.rst
docs/source/conf.py
docs/source/dependencies.rst
docs/source/index.rst
docs/source/installation.rst
docs/source/quickstart.rst
docs/source/related_projects.rst
knitout_to_dat_python/__init__.py
knitout_to_dat_python/dat_file_structure/Dat_to_Knitout_Converter.py
knitout_to_dat_python/dat_file_structure/__init__.py
knitout_to_dat_python/dat_file_structure/dat_bookend_sequences.py
knitout_to_dat_python/dat_file_structure/dat_codes/__init__.py
knitout_to_dat_python/dat_file_structure/dat_codes/dat_file_color_codes.py
knitout_to_dat_python/dat_file_structure/dat_codes/operation_colors.py
knitout_to_dat_python/dat_file_structure/dat_codes/option_lines.py
knitout_to_dat_python/dat_file_structure/dat_codes/option_value_colors.py
knitout_to_dat_python/dat_file_structure/knitout_to_dat_converter.py
knitout_to_dat_python/dat_file_structure/raster_carriage_passes/Outhook_Raster.py
knitout_to_dat_python/dat_file_structure/raster_carriage_passes/Pixel_Carriage_Pass_Converter.py
knitout_to_dat_python/dat_file_structure/raster_carriage_passes/Raster_Carriage_Pass.py
knitout_to_dat_python/dat_file_structure/raster_carriage_passes/Raster_Soft_Miss_Pass.py
knitout_to_dat_python/dat_file_structure/raster_carriage_passes/Releasehook_Raster.py
knitout_to_dat_python/dat_file_structure/raster_carriage_passes/__init__.py
knitout_to_dat_python/kickback_injection/__init__.py
knitout_to_dat_python/kickback_injection/kickback_execution.py
knitout_to_dat_python/knitout_to_dat.py
knitout_to_dat_python/py.typed
knitout_to_dat_python-0.0.4.dist-info/LICENSE
knitout_to_dat_python-0.0.4.dist-info/METADATA
knitout_to_dat_python-0.0.4.dist-info/WHEEL
knitout_to_dat_python-0.0.4.dist-info/RECORD
