Metadata-Version: 2.1
Name: knitout-to-dat-python
Version: 0.0.4
Summary: A tool replicating the functionality of the CMU Textile's Lab Knitout-to-Dat Interpreter implemented in Javascript. This python library can convert Knitout files into Shima Seiki DAT files.
Home-page: https://mhofmann-khoury.github.io/knitout_to_dat_python/
License: MIT
Keywords: knit,machine knit,textile,Northeastern,ACT Lab,fabrication,knitout
Author: Megan Hofmann
Author-email: m.hofmann@northeastern.edu
Maintainer: Megan Hofmann
Maintainer-email: m.hofmann@northeastern.edu
Requires-Python: >=3.11,<3.14
Classifier: Development Status :: 2 - Pre-Alpha
Classifier: Intended Audience :: Developers
Classifier: Intended Audience :: Manufacturing
Classifier: License :: OSI Approved :: MIT License
Classifier: Natural Language :: English
Classifier: Operating System :: OS Independent
Classifier: Programming Language :: Python :: 3
Classifier: Programming Language :: Python :: 3.11
Classifier: Programming Language :: Python :: 3.12
Classifier: Programming Language :: Python :: 3.13
Classifier: Topic :: Scientific/Engineering
Classifier: Typing :: Typed
Requires-Dist: knitout-interpreter (>=0.1.2)
Requires-Dist: virtual-knitting-machine (>=0.0.22)
Project-URL: Documentation, https://mhofmann-khoury.github.io/knitout_to_dat_python/
Project-URL: Repository, https://github.com/mhofmann-Khoury/knitout_to_dat_python
